setup.py
factlog/__init__.py
factlog/accessinfo.py
factlog/cli.py
factlog/config.py
factlog/database.py
factlog/filetitle.py
factlog/record.py
factlog.egg-info/PKG-INFO
factlog.egg-info/SOURCES.txt
factlog.egg-info/dependency_links.txt
factlog.egg-info/entry_points.txt
factlog.egg-info/requires.txt
factlog.egg-info/top_level.txt
factlog/tests/__init__.py
factlog/tests/test_accessinfo.py
factlog/tests/test_database.py
factlog/tests/test_filetitle.py
factlog/tests/test_record.py
factlog/utils/__init__.py
factlog/utils/iterutils.py
factlog/utils/py3compat.py
factlog/utils/strutils.py