Metadata-Version: 1.0
Name: factlog
Version: 0.0.1
Summary: factlog - File ACTivity LOGger
Home-page: https://github.com/tkf/factlog
Author: Takafumi Arakaki
Author-email: aka.tkf@gmail.com
License: GNU Lesser General Public License v3 (LGPLv3)
Keywords: history,recently used files
Platform: UNKNOWN
Classifier: Development Status :: 3 - Alpha
Classifier: Programming Language :: Python
Classifier: Programming Language :: Python :: 2
Classifier: Programming Language :: Python :: 2.6
Classifier: Programming Language :: Python :: 2.7
Classifier: Programming Language :: Python :: 3
Classifier: Programming Language :: Python :: 3.2
